{
  "lastUpdated": "2025-07-19T00:00:14.264Z",
  "stats": {
    "users": {
      "count": 47063,
      "change": 10.1
    },
    "revenue": {
      "amount": 212534,
      "change": 11.1
    },
    "projects": {
      "count": 365,
      "change": 0.9
    },
    "tasks": {
      "count": 2474,
      "change": 4.2
    }
  },
  "activities": [
    {
      "type": "message",
      "title": "Invoice generated",
      "timestamp": "2025-07-19T00:00:14.264Z"
    },
    {
      "type": "task",
      "title": "New message",
      "timestamp": "2025-07-18T00:01:01.082Z"
    },
    {
      "type": "alert",
      "title": "System alert",
      "timestamp": "2025-07-17T00:00:17.537Z"
    },
    {
      "type": "project",
      "title": "New user registered",
      "timestamp": "2025-07-16T00:00:56.630Z"
    },
    {
      "type": "alert",
      "title": "New message",
      "timestamp": "2025-07-15T00:00:24.625Z"
    }
  ],
  "weeklyActivity": [
    {
      "day": "Mon",
      "value": 29
    },
    {
      "day": "Tue",
      "value": 89
    },
    {
      "day": "Wed",
      "value": 17
    },
    {
      "day": "Thu",
      "value": 75
    },
    {
      "day": "Fri",
      "value": 58
    },
    {
      "day": "Sat",
      "value": 47
    },
    {
      "day": "Sun",
      "value": 84
    }
  ],
  "performanceMetrics": [
    {
      "date": "2023-10-08",
      "value": 11
    },
    {
      "date": "2023-10-09",
      "value": 10
    },
    {
      "date": "2023-10-10",
      "value": 40
    },
    {
      "date": "2023-10-11",
      "value": 39
    },
    {
      "date": "2023-10-12",
      "value": 11
    },
    {
      "date": "2023-10-13",
      "value": 37
    },
    {
      "date": "2023-10-14",
      "value": 14
    }
  ]
}