{
  "lastUpdated": "2025-09-06T00:00:16.279Z",
  "stats": {
    "users": {
      "count": 141725,
      "change": 14
    },
    "revenue": {
      "amount": 419812,
      "change": 9.3
    },
    "projects": {
      "count": 383,
      "change": 0.6
    },
    "tasks": {
      "count": 3136,
      "change": 13.7
    }
  },
  "activities": [
    {
      "type": "user",
      "title": "User updated profile",
      "timestamp": "2025-09-06T00:00:16.279Z"
    },
    {
      "type": "user",
      "title": "System alert",
      "timestamp": "2025-09-05T00:00:59.289Z"
    },
    {
      "type": "task",
      "title": "Project created",
      "timestamp": "2025-09-04T00:00:50.699Z"
    },
    {
      "type": "message",
      "title": "Task assigned",
      "timestamp": "2025-09-03T00:00:10.732Z"
    },
    {
      "type": "project",
      "title": "User updated profile",
      "timestamp": "2025-09-02T00:00:49.714Z"
    }
  ],
  "weeklyActivity": [
    {
      "day": "Mon",
      "value": 100
    },
    {
      "day": "Tue",
      "value": 82
    },
    {
      "day": "Wed",
      "value": 35
    },
    {
      "day": "Thu",
      "value": 29
    },
    {
      "day": "Fri",
      "value": 45
    },
    {
      "day": "Sat",
      "value": 33
    },
    {
      "day": "Sun",
      "value": 62
    }
  ],
  "performanceMetrics": [
    {
      "date": "2023-11-25",
      "value": 17
    },
    {
      "date": "2023-11-26",
      "value": 13
    },
    {
      "date": "2023-11-27",
      "value": 14
    },
    {
      "date": "2023-11-28",
      "value": 38
    },
    {
      "date": "2023-11-29",
      "value": 27
    },
    {
      "date": "2023-11-30",
      "value": 41
    },
    {
      "date": "2023-12-01",
      "value": 17
    }
  ]
}